{
  "db_name": "PostgreSQL",
  "query": "\n        SELECT r.id AS \"id!\", r.name AS \"name!\", r.slug\n        FROM roles r\n        JOIN cats_roles cr ON cr.role_id = r.id\n        WHERE cr.cat_id = $1\n        ORDER BY r.name ASC\n        ",
  "describe": {
    "columns": [
      {
        "ordinal": 0,
        "name": "id!",
        "type_info": "Uuid"
      },
      {
        "ordinal": 1,
        "name": "name!",
        "type_info": "Varchar"
      },
      {
        "ordinal": 2,
        "name": "slug",
        "type_info": "Varchar"
      }
    ],
    "parameters": {
      "Left": [
        "Uuid"
      ]
    },
    "nullable": [
      false,
      false,
      false
    ]
  },
  "hash": "2f728e2ba5e194e7ae2e7013f41ab465031c058dce07f91a9f05e337542d0b7d"
}
